mistral_ocr_pdf.py
mistral_ocr_pdf-0.1.0.dist-info/METADATA
mistral_ocr_pdf-0.1.0.dist-info/WHEEL
mistral_ocr_pdf-0.1.0.dist-info/entry_points.txt
mistral_ocr_pdf-0.1.0.dist-info/licenses/LICENSE
mistral_ocr_pdf-0.1.0.dist-info/RECORD
