Metadata-Version: 2.4
Name: mistral-ocr-pdf
Version: 0.1.0
Summary: CLI tool to convert PDFs to markdown using Mistral OCR
Author: reorx
License: MIT
License-File: LICENSE
Requires-Python: >=3.8
Requires-Dist: mistralai>=0.0.12
